gempaterkini/__init__.py
latestIndonesiaearthquake_officiL-0.0.1.dist-info/LICENSE
latestIndonesiaearthquake_officiL-0.0.1.dist-info/METADATA
latestIndonesiaearthquake_officiL-0.0.1.dist-info/WHEEL
latestIndonesiaearthquake_officiL-0.0.1.dist-info/top_level.txt
latestIndonesiaearthquake_officiL-0.0.1.dist-info/RECORD
