Metadata-Version: 2.1
Name: latestIndonesiaearthquake-officiL
Version: 0.0.1
Summary: This package will gate the latest earthquake from BMKG | Meteorological, Climatological, and Geophysical Agency.
Author-email: officialniepep@gmail.com
Classifier: Programming Language :: Python :: 3
Classifier: License :: OSI Approved :: MIT License
Classifier: Operating System :: OS Independent
License-File: LICENSE
